master_screen/__init__.py
master_screen/__main__.py
master_screen/version.py
master_screen/data/logger.ini
master_screen-0.0.1.data/scripts/master-screen
master_screen-0.0.1.dist-info/LICENSE
master_screen-0.0.1.dist-info/METADATA
master_screen-0.0.1.dist-info/WHEEL
master_screen-0.0.1.dist-info/entry_points.txt
master_screen-0.0.1.dist-info/top_level.txt
master_screen-0.0.1.dist-info/RECORD
